jlgametheory/__init__.py
jlgametheory/jlgametheory.py
jlgametheory/juliapkg.json
jlgametheory-0.1.1.dist-info/licenses/LICENSE
jlgametheory-0.1.1.dist-info/WHEEL
jlgametheory-0.1.1.dist-info/METADATA
jlgametheory-0.1.1.dist-info/RECORD
