Metadata-Version: 2.4
Name: jlgametheory
Version: 0.1.1
Summary: Python interface to GameTheory.jl
Author: QuantEcon
Requires-Python: >=3.10
Classifier: Development Status :: 3 - Alpha
Classifier: Intended Audience :: Science/Research
Classifier: License :: OSI Approved :: BSD License
Classifier: Programming Language :: Python :: 3
Classifier: Programming Language :: Python :: 3.10
Classifier: Programming Language :: Python :: 3.11
Classifier: Programming Language :: Python :: 3.12
Classifier: Programming Language :: Python :: 3.13
Classifier: Programming Language :: Python :: 3.14
Classifier: Topic :: Scientific/Engineering
License-File: LICENSE
Requires-Dist: numpy>=1.22
Requires-Dist: quantecon>=0.8
Requires-Dist: juliacall>=0.9.20
Requires-Dist: sphinx>=8.0 ; extra == "docs"
Requires-Dist: sphinx-copybutton ; extra == "docs"
Requires-Dist: pytest>=7 ; extra == "test"
Requires-Dist: pytest-cov>=4 ; extra == "test"
Project-URL: Homepage, https://github.com/QuantEcon/jlgametheory
Project-URL: Repository, https://github.com/QuantEcon/jlgametheory
Provides-Extra: docs
Provides-Extra: test
